media_fetcher/__init__.py
media_fetcher/instagram.py
media_fetcher/tiktok.py
media_fetcher-0.1.0.dist-info/LICENSE
media_fetcher-0.1.0.dist-info/METADATA
media_fetcher-0.1.0.dist-info/WHEEL
media_fetcher-0.1.0.dist-info/RECORD
