Metadata-Version: 2.1
Name: media-fetcher
Version: 0.1.0
Summary: A Python package for fetching media details from Instagram, TikTok, and other platforms.
Home-page: https://github.com/xl-spooky/media-fetcher
License: MIT
Keywords: media,fetcher,instagram,tiktok,social media
Author: xl_spooky
Author-email: spkydevelopment@gmail.com
Requires-Python: >=3.11,<4.0
Classifier: License :: OSI Approved :: MIT License
Classifier: Programming Language :: Python :: 3
Classifier: Programming Language :: Python :: 3.11
Classifier: Programming Language :: Python :: 3.12
Classifier: Programming Language :: Python :: 3.13
Requires-Dist: twine (>=5.1.1,<6.0.0)
Project-URL: Repository, https://github.com/xl-spooky/media-fetcher
